faculty_datasets_fs.py
faculty_datasets_fs-0.1.3.dist-info/METADATA
faculty_datasets_fs-0.1.3.dist-info/WHEEL
faculty_datasets_fs-0.1.3.dist-info/entry_points.txt
faculty_datasets_fs-0.1.3.dist-info/top_level.txt
faculty_datasets_fs-0.1.3.dist-info/RECORD
