Metadata-Version: 2.1
Name: faculty-datasets-fs
Version: 0.1.3
Summary: fsspec plugin for Faculty Datasets
Author-email: Faculty <info@faculty.ai>
Project-URL: company, https://faculty.ai
Requires-Python: >=3.10
Requires-Dist: faculty
Requires-Dist: fsspec
Requires-Dist: requests
